odoo_designer_scaffold/__init__.py
odoo_designer_scaffold/main.py
odoo_designer_scaffold-0.13.dist-info/METADATA
odoo_designer_scaffold-0.13.dist-info/WHEEL
odoo_designer_scaffold-0.13.dist-info/entry_points.txt
odoo_designer_scaffold-0.13.dist-info/top_level.txt
odoo_designer_scaffold-0.13.dist-info/RECORD
