Metadata-Version: 2.1
Name: odoo_designer_scaffold
Version: 0.13
